passlib/__init__.py
passrank-1.0.0.dist-info/licenses/LICENSE
passrank-1.0.0.dist-info/METADATA
passrank-1.0.0.dist-info/WHEEL
passrank-1.0.0.dist-info/top_level.txt
passrank-1.0.0.dist-info/RECORD
